magscreen/__init__.py
magscreen/calc.py
magscreen/common.py
magscreen/plot.py
magscreen/screen.py
magscreen/semcsv.py
magscreen/summary.py
magscreen/tlvmr.py
magscreen-0.3.dist-info/LICENSE
magscreen-0.3.dist-info/METADATA
magscreen-0.3.dist-info/WHEEL
magscreen-0.3.dist-info/entry_points.txt
magscreen-0.3.dist-info/top_level.txt
magscreen-0.3.dist-info/RECORD
