Metadata-Version: 2.1
Name: magscreen
Version: 0.3
Summary: Magnetic cleanliness screening via constant rotation.
Home-page: https://github.com/cpiker/magscreen
Author: C. Piker, C. Dorman
Author-email: cpiker@users.noreply.github.com, cjdorman@users.noreply.github.com
Requires-Python: >=3.6
License-File: LICENSE
Requires-Dist: numpy
Requires-Dist: scipy
Requires-Dist: matplotlib
Requires-Dist: tio
